sweetagent/__init__.py
sweetagent/core.py
sweetagent/llm_agent.py
sweetagent/llm_client.py
sweetagent/prompt.py
sweetagent/recursive_thought.py
sweetagent/utils.py
sweetagent/channels/__init__.py
sweetagent/io/__init__.py
sweetagent/io/base.py
sweetagent/io/redis.py
sweetagent/long_term_memory/__init__.py
sweetagent/long_term_memory/base.py
sweetagent/long_term_memory/memzero.py
sweetagent/long_term_memory/void.py
sweetagent/middlewares/__init__.py
sweetagent/middlewares/base.py
sweetagent/short_term_memory/__init__.py
sweetagent/short_term_memory/base.py
sweetagent/short_term_memory/session.py
sweetagent-0.1.3.dist-info/METADATA
sweetagent-0.1.3.dist-info/WHEEL
sweetagent-0.1.3.dist-info/licenses/LICENSE
sweetagent-0.1.3.dist-info/RECORD
