Metadata-Version: 2.4
Name: sweetagent
Version: 0.1.3
Summary: Pluggable LLM/AI Agent library
Author-email: Matt Jeff <jefcolbi@gmail.com>
License-File: LICENSE
Requires-Python: >=3.8
Requires-Dist: litellm>=1.65.7
Requires-Dist: python-decouple>=3.8
Requires-Dist: tokenizers<0.21
Requires-Dist: traceback-with-variables>=2.2.0
Requires-Dist: trender>=1.0.10
Provides-Extra: channels
Requires-Dist: channels>=4.2.2; extra == 'channels'
Requires-Dist: daphne>=4.1.2; extra == 'channels'
Provides-Extra: mem0
Requires-Dist: mem0ai; extra == 'mem0'
Provides-Extra: redis
Requires-Dist: redis; extra == 'redis'
